{
  "total": 10,
  "pending": 10,
  "processing": 0,
  "completed": 0,
  "failed": 0,
  "last_updated": "2026-05-23T02:58:13.482130+00:00",
  "last_wal_seq": 10,
  "snapshot_created_at": "2026-05-23T02:58:13.482130+00:00",
  "snapshot_item_counts": {
    "pending": 10,
    "processing": 0,
    "completed": 0,
    "failed": 0
  },
  "wal_compaction_count": 0,
  "replay_operation_count": 0,
  "items": [
    {
      "cache_key": "5d4d87ba1fb702d08f528a0660ceb62d",
      "protocol_version": "1.0",
      "article_id": "1",
      "stage": "ec",
      "status": "PENDING",
      "priority": 0,
      "title": "Practical Perspectives on Fairness In Technology-Aided Personnel Selection",
      "abstract": "The widespread integration of data-driven technologies in hiring highlights the need for appropriate fairness assessment methodologies. With AI applications in hiring classified as high-risk systems in the European Union, vendors are compelled to manage discrimination risks carefully throughout development and integration in personnel selection. This necessitates a critical examination of how fairness is conceptualized and operationalized in hiring practice. By conducting group and individual interviews with diverse stakeholders in the German-speaking market, our research evaluates the alignment between technical research findings and industry expectations and practices, as well as the congruence of stakeholder perspectives, especially HR practitioners and technology developers.Our findings underscore the influence of organizational norms and diversity goals on practitioners' fairness conceptions, adding complexity to the already fragmented landscape. While all participants endorsed normative principles such as transparency and standardization, many lacked awareness of the limitations and challenges of implementing them in practice. Concrete operationalization of fairness emerged as a challenge for almost all participants, particularly HR practitioners, who showed limited familiarity with fairness metrics and often expressed skepticism toward both group-level and individual-level measures.This study highlights the necessity for stronger engagement with HR departments in fairness and technology research. We argue that ensuring fairness in AI-assisted hiring requires shared vocabularies, configurable fairness evaluations, targeted training, and collaborative infrastructures to enable robust and effective oversight of the development and usage of these technologies.",
      "created_at": "2026-05-23T02:58:13.422048+00:00",
      "started_at": null,
      "completed_at": null,
      "retry_count": 0,
      "last_error": null,
      "retry_after": null,
      "retry_reason": null,
      "is_quarantined": false
    },
    {
      "cache_key": "efaba0b5b37c9175e87a6e45e2befd08",
      "protocol_version": "1.0",
      "article_id": "2",
      "stage": "ec",
      "status": "PENDING",
      "priority": 1,
      "title": "Acrobats and Safety Nets: Problematizing Large-Scale Agile Software Development",
      "abstract": "Agile development methods have become a standard in the software industry, including in large-scale projects. These methods share a set of underlying assumptions that distinguish them from more traditional plan-driven approaches. In this article, we adopt Alvesson and Sandberg's problematization approach to challenge three key assumptions that are prevalent in the large-scale agile literature: (1) agile and plan-driven methods are mutually exclusive; (2) self-managing and hierarchically organized teams are mutually exclusive; and (3) agile methods can scale through simple linear composition. Using a longitudinal case study of large-scale agile development, we describe a series of trigger events and episodes whereby the agile approach was tailored to address the needs of the large-scale development context, which was very much at odds with these fundamental assumptions. We develop a set of new underlying assumptions which suggest that agile and plan-driven practices are mutually enabling and necessary for coordination and scaling in large-scale agile projects. We develop nine propositions for large-scale agile projects based on these new alternative underlying assumptions. Finally, we summarize our theoretical contribution in a generic process model of continuously adjusting agile and plan-driven practices in order to accommodate process challenges in large-scale agile projects.",
      "created_at": "2026-05-23T02:58:13.422077+00:00",
      "started_at": null,
      "completed_at": null,
      "retry_count": 0,
      "last_error": null,
      "retry_after": null,
      "retry_reason": null,
      "is_quarantined": false
    },
    {
      "cache_key": "28c4db96003b5903c2fb42d597343822",
      "protocol_version": "1.0",
      "article_id": "3",
      "stage": "ec",
      "status": "PENDING",
      "priority": 2,
      "title": "Making Software Development More Diverse and Inclusive: Key Themes, Challenges, and Future Directions",
      "abstract": "Introduction: Digital products increasingly reshape industries, influencing human behavior and decision-making. However, the software development teams developing these systems often lack diversity, which may lead to designs that overlook the needs, equal treatment or safety of diverse user groups. These risks highlight the need for fostering diversity and inclusion in software development to create safer, more equitable technology.Method: This research is based on insights from an academic meeting in June 2023 involving 23 software engineering researchers and practitioners. We used the collaborative discussion method 1-2-4-ALL as a systematic research approach and identified six themes around the theme “challenges and opportunities to improve Software Developer Diversity and Inclusion (SDDI).” We identified benefits, harms, and future research directions for the four main themes. Then, we discuss the remaining two themes, AI &amp; SDDI and AI &amp; Computer Science education, which have a cross-cutting effect on the other themes.Results: This research explores the key challenges and research opportunities for promoting SDDI, providing a roadmap to guide both researchers and practitioners. We underline that research around SDDI requires a constant focus on maximizing benefits while minimizing harms, especially to vulnerable groups. As a research community, we must strike this balance in a responsible way.",
      "created_at": "2026-05-23T02:58:13.422109+00:00",
      "started_at": null,
      "completed_at": null,
      "retry_count": 0,
      "last_error": null,
      "retry_after": null,
      "retry_reason": null,
      "is_quarantined": false
    },
    {
      "cache_key": "35d36ceae49bbbee3f168fb46de8ddaf",
      "protocol_version": "1.0",
      "article_id": "4",
      "stage": "ec",
      "status": "PENDING",
      "priority": 3,
      "title": "Gender and Participation in Open Source Software Development",
      "abstract": "Open source software represents an important form of digital infrastructure as well as a pathway to technical careers for many developers, but women are drastically underrepresented in this setting. Although there is a good body of literature on open source participation, there is very little understanding of the participation trajectories and contribution experiences of women developers, and how they compare to those of men developers, in open source software projects. In order to understand their joining and participation trajectories, we conducted interviews with 23 developers (11 men and 12 women) who became core in an open source project. We identify differences in women and men's motivations for initial contributions and joining processes (e.g. women participating in projects that they have been invited to) and sustained involvement in a project. We also describe unique negative experiences faced by women contributors in this setting in each stage of participation. Our results have implications for diversifying participation in open source software and understanding open source as a pathway to technical careers.",
      "created_at": "2026-05-23T02:58:13.422123+00:00",
      "started_at": null,
      "completed_at": null,
      "retry_count": 0,
      "last_error": null,
      "retry_after": null,
      "retry_reason": null,
      "is_quarantined": false
    },
    {
      "cache_key": "31cb607d959c306f102299cb40a8a8fd",
      "protocol_version": "1.0",
      "article_id": "5",
      "stage": "ec",
      "status": "PENDING",
      "priority": 4,
      "title": "ConE: A Concurrent Edit Detection Tool for Large-scale Software Development",
      "abstract": "Modern, complex software systems are being continuously extended and adjusted. The developers responsible for this may come from different teams or organizations, and may be distributed over the world. This may make it difficult to keep track of what other developers are doing, which may result in multiple developers concurrently editing the same code areas. This, in turn, may lead to hard-to-merge changes or even merge conflicts, logical bugs that are difficult to detect, duplication of work, and wasted developer productivity. To address this, we explore the extent of this problem in the pull-request-based software development model. We study half a year of changes made to six large repositories in Microsoft in which at least 1,000 pull requests are created each month. We find that files concurrently edited in different pull requests are more likely to introduce bugs. Motivated by these findings, we design, implement, and deploy a service named Concurrent Edit Detector (ConE) that proactively detects pull requests containing concurrent edits, to help mitigate the problems caused by them. ConE has been designed to scale, and to minimize false alarms while still flagging relevant concurrently edited files. Key concepts of ConE include the detection of the Extent of Overlap between pull requests, and the identification of Rarely Concurrently Edited Files. To evaluate ConE, we report on its operational deployment on 234 repositories inside Microsoft. ConE assessed 26,000 pull requests and made 775 recommendations about conflicting changes, which were rated as useful in over 70% (554) of the cases. From interviews with 48 users, we learned that they believed ConE would save time in conflict resolution and avoiding duplicate work, and that over 90% intend to keep using the service on a daily basis.",
      "created_at": "2026-05-23T02:58:13.422137+00:00",
      "started_at": null,
      "completed_at": null,
      "retry_count": 0,
      "last_error": null,
      "retry_after": null,
      "retry_reason": null,
      "is_quarantined": false
    },
    {
      "cache_key": "9e27835f83bcef4c9cae5487912ccf83",
      "protocol_version": "1.0",
      "article_id": "6",
      "stage": "ec",
      "status": "PENDING",
      "priority": 5,
      "title": "SnappView, a Software Development Kit for Supporting End-user Mobile Interface Review",
      "abstract": "This paper presents SnappView, an open-source software development kit that facilitates end-user review of graphical user interfaces for mobile applications and streamlines their input into a continuous design life cycle. SnappView structures this user interface review process into four cumulative stages: (1) a developer creates a mobile application project with user interface code instrumented by only a few instructions governing SnappView and deploys the resulting application on an application store; (2) any tester, such as an end-user, a designer, a reviewer, while interacting with the instrumented user interface, shakes the mobile device to freeze and capture its screen and to provide insightful multimodal feedback such as textual comments, critics, suggestions, drawings by stroke gestures, voice or video records, with a level of importance; (3) the screenshot is captured with the application, browser, and status data and sent with the feedback to SnappView server; and (4) a designer then reviews collected and aggregated feedback data and passes them to the developer to address raised usability problems. Another cycle then initiates an iterative design. This paper presents the motivations and process for performing mobile application review based on SnappView. Based on this process, we deployed on the AppStore \"WeTwo\", a real-world mobile application to find various personal activities over a one-month period with 420 active users. This application served for a user experience evaluation conducted with N1=14 developers to reveal the advantages and shortcomings of the toolkit from a development point of view. The same application was also used in a usability evaluation conducted with N2=22 participants to reveal the advantages and shortcomings from an end-user viewpoint.",
      "created_at": "2026-05-23T02:58:13.422151+00:00",
      "started_at": null,
      "completed_at": null,
      "retry_count": 0,
      "last_error": null,
      "retry_after": null,
      "retry_reason": null,
      "is_quarantined": false
    },
    {
      "cache_key": "619a24a4944538946524bc63fd1b7c31",
      "protocol_version": "1.0",
      "article_id": "7",
      "stage": "ec",
      "status": "PENDING",
      "priority": 6,
      "title": "Exploring and Expanding GSE Education with Open Source Software Development",
      "abstract": "Global software engineering (GSE) courses traditionally require cooperation between at least two universities so as to provide a distributed development environment to the students. In this study, we explore an alternative way to organize a global software engineering course where students work on open source software development (OSSD) projects rather than in a multi-university collaboration setting. The results show that the new setup may provide core GSE challenges as well as challenges associated with software development outsourcing and challenges related to working on large open source software. The present article compares the experiences gained from running a combined GSE and OSSD course against the experiences gained from running a traditional GSE course. The two alternatives are compared in terms of students’ learning outcomes and course organization. The authors found that a combined GSE and OSSD course provides learning opportunities that are partly overlapping with, and partly complementary to, a traditional GSE course. The authors also found that the combined OSSD and GSE course was somewhat easier to organize because most of the activities took place in a single university setting. The authors used the extended GSE taxonomy for the comparison and found it to be a useful tool for this, although it had some limitations in expressive power. Therefore, two additional relationship dimensions are proposed that will further enrich the extended taxonomy in classifying GSE (and OSSD) projects.",
      "created_at": "2026-05-23T02:58:13.422176+00:00",
      "started_at": null,
      "completed_at": null,
      "retry_count": 0,
      "last_error": null,
      "retry_after": null,
      "retry_reason": null,
      "is_quarantined": false
    },
    {
      "cache_key": "1409632b4c1022f408b14a700f3bf0b4",
      "protocol_version": "1.0",
      "article_id": "8",
      "stage": "ec",
      "status": "PENDING",
      "priority": 7,
      "title": "Towards a Conceptual Framework for Security Requirements Work in Agile Software Development",
      "abstract": "Security requirement work plays a key role in achieving cost-effective and adequate security in a software development project. Knowledge about software companies' experiences of security requirement work is important in order to bridge the observed gap between software security practices and security risks in many projects today. Particularly, such knowledge can help researchers improve on available practices and recommendations. This article uses the results of published empirical studies on security requirement work to create a conceptual framework that shows key concepts related to work context, this work itself and the effects of this work. The resulting framework points to the following research challenges: 1) Identifying and understanding factors important for the effect of security requirements work; 2) Understanding what is the importance of the chosen requirements approach itself, and; 3) Properly taking into account contextual factors, especially factors related to individuals and interactions, in planning and analysis of empirical studies on security requirements work.",
      "created_at": "2026-05-23T02:58:13.422188+00:00",
      "started_at": null,
      "completed_at": null,
      "retry_count": 0,
      "last_error": null,
      "retry_after": null,
      "retry_reason": null,
      "is_quarantined": false
    },
    {
      "cache_key": "e9c4785561cc4f10effbb388f99a30c8",
      "protocol_version": "1.0",
      "article_id": "9",
      "stage": "ec",
      "status": "PENDING",
      "priority": 8,
      "title": "Fairness and Bias in Algorithmic Hiring: A Multidisciplinary Survey",
      "abstract": "Employers are adopting algorithmic hiring technology throughout the recruitment pipeline. Algorithmic fairness is especially applicable in this domain due to its high stakes and structural inequalities. Unfortunately, most work in this space provides partial treatment, often constrained by two competing narratives, optimistically focused on replacing biased recruiter decisions or pessimistically pointing to the automation of discrimination. Whether, and more importantly what types of, algorithmic hiring can be less biased and more beneficial to society than low-tech alternatives currently remains unanswered, to the detriment of trustworthiness. This multidisciplinary survey caters to practitioners and researchers with a balanced and integrated coverage of systems, biases, measures, mitigation strategies, datasets, and legal aspects of algorithmic hiring and fairness. Our work supports a contextualized understanding and governance of this technology by highlighting current opportunities and limitations, providing recommendations for future work to ensure shared benefits for all stakeholders.",
      "created_at": "2026-05-23T02:58:13.422200+00:00",
      "started_at": null,
      "completed_at": null,
      "retry_count": 0,
      "last_error": null,
      "retry_after": null,
      "retry_reason": null,
      "is_quarantined": false
    },
    {
      "cache_key": "c2642cf2c7c7748094d143460f6e7159",
      "protocol_version": "1.0",
      "article_id": "10",
      "stage": "ec",
      "status": "PENDING",
      "priority": 9,
      "title": "Hiring CS Graduates: What We Learned from Employers",
      "abstract": "Computer science (CS) majors are in high demand and account for a large part of national computer and information technology job market applicants. Employment in this sector is projected to grow 12% between 2018 and 2028, which is faster than the average of all other occupations. Published data are available on traditional non-computer science-specific hiring processes. However, the hiring process for CS majors may be different. It is critical to have up-to-date information on questions such as “what positions are in high demand for CS majors?,” “what is a typical hiring process?,” and “what do employers say they look for when hiring CS graduates?” This article discusses the analysis of a survey of 218 recruiters hiring CS graduates in the United States. We used Atlas.ti to analyze qualitative survey data and report the results on what positions are in the highest demand, the hiring process, and the resume review process. Our study revealed that a software developer was the most common job the recruiters were looking to fill. We found that the hiring process steps for CS graduates are generally aligned with traditional hiring steps, with an additional emphasis on technical and coding tests. Recruiters reported that their hiring choices were based on reviewing resume’s experience, GPA, and projects sections. The results provide insights into the hiring process, decision making, resume analysis, and some discrepancies between current undergraduate CS program outcomes and employers’ expectations.",
      "created_at": "2026-05-23T02:58:13.422222+00:00",
      "started_at": null,
      "completed_at": null,
      "retry_count": 0,
      "last_error": null,
      "retry_after": null,
      "retry_reason": null,
      "is_quarantined": false
    }
  ]
}